nanoprofiler/__init__.py
nanoprofiler/profiler.py
nanoprofiler-0.2.1.dist-info/LICENSE
nanoprofiler-0.2.1.dist-info/METADATA
nanoprofiler-0.2.1.dist-info/WHEEL
nanoprofiler-0.2.1.dist-info/top_level.txt
nanoprofiler-0.2.1.dist-info/RECORD
