Metadata-Version: 2.1
Name: nanoprofiler
Version: 0.2.1
Summary: A small python profiler using cProfile, pstats, Pandas and matplotlib.
Home-page: https://nanogennari.gitlab.io/nanoprofiler/
Author: nano
Author-email: me@nngn.net
License: UNKNOWN
Platform: UNKNOWN
Classifier: Development Status :: 4 - Beta
Classifier: Programming Language :: Python :: 3
Classifier: License :: OSI Approved :: GNU General Public License v3 (GPLv3)
Classifier: Operating System :: OS Independent
Requires-Python: >=3.6
Requires-Dist: matplotlib (>=3.3.1)
Requires-Dist: pandas (>=1.1.1)
